specpolFlow/__init__.py
specpolFlow/cleanMaskUI.py
specpolFlow/cleanMaskUISubroutines.py
specpolFlow/lineList.py
specpolFlow/mask.py
specpolFlow/obsSpec.py
specpolFlow/profileLSD.py
specpolFlow/CommandLine/__init__.py
specpolFlow/CommandLine/bz.py
specpolFlow/CommandLine/cleanMaskUI.py
specpolFlow/CommandLine/convertEspadons.py
specpolFlow/CommandLine/convertSpirou.py
specpolFlow/CommandLine/makeMask.py
specpolFlow/CommandLine/plotLSD.py
specpolFlow/CommandLine/rvFit.py
specpolFlow/converters/__init__.py
specpolFlow/converters/espadons.py
specpolFlow/converters/spirou.py
specpolflow-1.0.0.dist-info/licenses/LICENSE
specpolflow-1.0.0.dist-info/METADATA
specpolflow-1.0.0.dist-info/WHEEL
specpolflow-1.0.0.dist-info/entry_points.txt
specpolflow-1.0.0.dist-info/top_level.txt
specpolflow-1.0.0.dist-info/RECORD
