Metadata-Version: 2.4
Name: specpolFlow
Version: 1.0.0
Summary: Tools for the analysis of stellar spectropolarimetric data
Author-email: SpecpolFlow Team <specpolflow@gmail.com>
License-Expression: GPL-2.0-or-later
Project-URL: Homepage, https://github.com/folsomcp/specpolFlow
Project-URL: Documentation, https://folsomcp.github.io/specpolFlow/
Classifier: Development Status :: 5 - Production/Stable
Classifier: Intended Audience :: Science/Research
Classifier: Topic :: Scientific/Engineering :: Astronomy
Classifier: Programming Language :: Python :: 3
Requires-Python: >=3.8
License-File: LICENSE
Requires-Dist: numpy
Requires-Dist: scipy
Requires-Dist: matplotlib
Requires-Dist: astropy
Requires-Dist: LSDpy
Provides-Extra: norm
Requires-Dist: normPlot; extra == "norm"
Dynamic: license-file
